setup.py
distributions_gauss_bi/Binomialdistribution.py
distributions_gauss_bi/Gaussiandistribution.py
distributions_gauss_bi/Generaldistribution.py
distributions_gauss_bi/__init__.py
distributions_gauss_bi.egg-info/PKG-INFO
distributions_gauss_bi.egg-info/SOURCES.txt
distributions_gauss_bi.egg-info/dependency_links.txt
distributions_gauss_bi.egg-info/not-zip-safe
distributions_gauss_bi.egg-info/top_level.txt