Metadata-Version: 1.0
Name: distributions-gauss-bi
Version: 0.0.2
Summary: Gaussian and Binomial distributions
Home-page: UNKNOWN
Author: Jones Mbindyo
Author-email: rocqjones@gmail.com
License: UNKNOWN
Platform: UNKNOWN
